snitch/__init__.py
snitch/logger.py
snitch/main.py
snitch/typed.py
snitch/parsers/__init__.py
snitch/parsers/config_parser.py
snitch/parsers/openapi_parser.py
snitch/parsers/parser_exceptions.py
snitch/parsers/postman_parser.py
snitch/parsers/request_model.py
snitch/scripts/generate_config_json_template.py
snitch/task_runners/__init__.py
snitch/task_runners/health_check.py
snitch/task_runners/idempotency_check.py
snitch/task_runners/report_builder.py
snitch/task_runners/task.py
api_snitch-0.1.34.dist-info/METADATA
api_snitch-0.1.34.dist-info/WHEEL
api_snitch-0.1.34.dist-info/entry_points.txt
api_snitch-0.1.34.dist-info/licenses/LICENSE
api_snitch-0.1.34.dist-info/RECORD
