Metadata-Version: 2.1
Name: api-snitch
Version: 0.1.34
Summary: snitch is a CLI tool that helps you do health check, API idempotency check and more for your APIs.
Project-URL: Homepage, https://github.com/ccwukong/snitch
Project-URL: Bug Tracker, https://github.com/ccwukong/snitch/issues
Author-email: Chen Cheng <ccwukong@gmail.com>
License-File: LICENSE
Classifier: License :: OSI Approved :: MIT License
Classifier: Operating System :: OS Independent
Classifier: Programming Language :: Python :: 3
Requires-Python: >=3.8
Requires-Dist: aiohttp
Requires-Dist: anyio
Requires-Dist: asyncclick
Requires-Dist: chardet
Requires-Dist: pyyaml
Requires-Dist: requests
Requires-Dist: urllib3
